autointent/__init__.py
autointent/_callbacks/__init__.py
autointent/_callbacks/base.py
autointent/_callbacks/callback_handler.py
autointent/_callbacks/emissions_tracker.py
autointent/_callbacks/tensorboard.py
autointent/_callbacks/wandb.py
autointent/_dataset/__init__.py
autointent/_dataset/_dataset.py
autointent/_dataset/_reader.py
autointent/_dataset/_validation.py
autointent/_dump_tools/__init__.py
autointent/_dump_tools/base.py
autointent/_dump_tools/generator_dumper.py
autointent/_dump_tools/main.py
autointent/_dump_tools/unit_dumpers.py
autointent/_hash.py
autointent/_logging/__init__.py
autointent/_logging/config.yaml
autointent/_logging/formatter.py
autointent/_logging/setup.py
autointent/_optimization_config.py
autointent/_pipeline/__init__.py
autointent/_pipeline/_pipeline.py
autointent/_pipeline/_schemas.py
autointent/_presets/__init__.py
autointent/_presets/classic-heavy.yaml
autointent/_presets/classic-light.yaml
autointent/_presets/classic-medium.yaml
autointent/_presets/nn-heavy.yaml
autointent/_presets/nn-medium.yaml
autointent/_presets/transformers-heavy.yaml
autointent/_presets/transformers-light.yaml
autointent/_presets/transformers-no-hpo.yaml
autointent/_presets/zero-shot-encoders.yaml
autointent/_presets/zero-shot-llm.yaml
autointent/_utils.py
autointent/_wrappers/__init__.py
autointent/_wrappers/base_torch_module.py
autointent/_wrappers/embedder.py
autointent/_wrappers/ranker.py
autointent/_wrappers/vector_index.py
autointent/configs/__init__.py
autointent/configs/_inference_node.py
autointent/configs/_name.py
autointent/configs/_optimization.py
autointent/configs/_torch.py
autointent/configs/_transformers.py
autointent/context/__init__.py
autointent/context/_context.py
autointent/context/_utils.py
autointent/context/data_handler/__init__.py
autointent/context/data_handler/_data_handler.py
autointent/context/data_handler/_stratification.py
autointent/context/optimization_info/__init__.py
autointent/context/optimization_info/_data_models.py
autointent-0.2.0.dist-info/LICENSE
autointent-0.2.0.dist-info/METADATA
autointent-0.2.0.dist-info/WHEEL
autointent-0.2.0.dist-info/entry_points.txt
autointent-0.2.0.dist-info/RECORD
